fontimize.py
fontimize-0.8.9.dist-info/METADATA
fontimize-0.8.9.dist-info/WHEEL
fontimize-0.8.9.dist-info/licenses/LICENSE
fontimize-0.8.9.dist-info/RECORD
