Metadata-Version: 2.1
Name: fontimize
Version: 0.8.9
Summary: Easily create font subsets containing only characters used in your text or website
Project-URL: Homepage, https://github.com/vintagedave/fontimize
Project-URL: Issues, https://github.com/vintagedave/fontimize/issues
Project-URL: Website, https://fontimize.daveon.design
Author-email: David Millington <vintagedave@gmail.com>
License:                     GNU GENERAL PUBLIC LICENSE
License-File: LICENSE
Keywords: characters,font,glyphs,minimization,minimize,minimizer,optimization,optimize,ssg,subset,web
Classifier: Development Status :: 4 - Beta
Classifier: License :: OSI Approved :: GNU General Public License v3 (GPLv3)
Classifier: Operating System :: OS Independent
Classifier: Programming Language :: Python :: 3
Classifier: Topic :: Text Processing :: Fonts
Requires-Dist: bs4
Requires-Dist: pathlib
Requires-Dist: pathvalidate
Requires-Dist: tinycss2
Requires-Dist: ttf2web
Requires-Dist: typing
